{
    "name": "Enforce Kubelet client TLS authentication",
    "attributes": {
        "armoBuiltin": true,
        "controlTypeTags": [
            "security",
            "compliance"
        ],
        "attackTracks": [
            {
                "attackTrack": "node",
                "categories": [
                    "Initial access"
                ]
            }
        ]
    },
    "description": "Kubelets are the node level orchestrator in Kubernetes control plane. They are publishing service port 10250 where they accept commands from API server. Operator must make sure that only API server is allowed to submit commands to Kubelet. This is done through client certificate verification, must configure Kubelet with client CA file to use for this purpose.",
    "remediation": "Start the kubelet with the --client-ca-file flag, providing a CA bundle to verify client certificates with.",
    "rulesNames": [
        "enforce-kubelet-client-tls-authentication-updated"
    ],
    "long_description": "Kubelets are the node level orchestrator in Kubernetes control plane. They are publishing service port 10250 where they accept commands from API server. Operator must make sure that only API server is allowed to submit commands to Kubelet. This is done through client certificate verification, must configure Kubelet with client CA file to use for this purpose.",
    "test": "Reading the kubelet command lines and configuration file looking for client TLS configuration.",
    "controlID": "C-0070",
    "baseScore": 9.0,
    "category": {
        "name" : "Control plane"
   }
}